czh/__init__.py
czh/beautiful/__init__.py
czh/beautiful/message.py
lch_czh-0.1.dist-info/METADATA
lch_czh-0.1.dist-info/WHEEL
lch_czh-0.1.dist-info/top_level.txt
lch_czh-0.1.dist-info/RECORD
