Metadata-Version: 2.1
Name: lch-czh
Version: 0.1
Summary: 李翠华，陈泽华
Author: lch
License: UNKNOWN
Platform: UNKNOWN
